taskorchestrator/__init__.py
taskorchestrator/core.py
taskorchestrator/exceptions.py
taskorchestrator/hooks.py
taskorchestrator-1.0.0.dist-info/LICENSE
taskorchestrator-1.0.0.dist-info/METADATA
taskorchestrator-1.0.0.dist-info/WHEEL
taskorchestrator-1.0.0.dist-info/top_level.txt
taskorchestrator-1.0.0.dist-info/RECORD
