Metadata-Version: 2.2
Name: taskorchestrator
Version: 1.0.0
Summary: A library for managing workflows of asynchronous tasks.
Author-email: Walter Avelino <walter.avelin@gmail.com>
Classifier: Programming Language :: Python :: 3.12
Classifier: License :: OSI Approved :: MIT License
Classifier: Operating System :: OS Independent
Requires-Python: >=3.12
License-File: LICENSE
Requires-Dist: typing-extensions>=4.0.0
